jupyter_parser.py
jupyter_parser-0.0a2.dist-info/DESCRIPTION.rst
jupyter_parser-0.0a2.dist-info/METADATA
jupyter_parser-0.0a2.dist-info/RECORD
jupyter_parser-0.0a2.dist-info/WHEEL
jupyter_parser-0.0a2.dist-info/entry_points.txt
jupyter_parser-0.0a2.dist-info/metadata.json
jupyter_parser-0.0a2.dist-info/top_level.txt
parsers/JupyterParser.py
parsers/__init__.py
parsers/utility.py
plugins/CellsCorrectPlugin.py
plugins/NotebookLibrariesPlugin.py
plugins/NotebookSparkPlugin.py
plugins/__init__.py
