Metadata-Version: 2.0
Name: jupyter-parser
Version: 0.0a2
Summary: a command line tool for parsing jupyter notebooks
Home-page: https://github.com/cameres/jupyter-parser
Author: Connor Ameres
Author-email: connorameres@gmail.com
License: Mozilla Public License 2.0 (MPL 2.0)
Keywords: jupyter notebook parser plugins
Platform: UNKNOWN
Classifier: Development Status :: 3 - Alpha
Classifier: License :: OSI Approved :: Mozilla Public License 2.0 (MPL 2.0)
Classifier: Topic :: Software Development
Classifier: Programming Language :: Python :: 2.7
Classifier: Programming Language :: Python :: 3.5
Requires-Dist: click
